plexus/msgs/__init__.py
plexus/msgs/__main__.py
plexus/msgs/descriptor.pb
plexus/msgs/plexus_common_carto_pb2.py
plexus/msgs/plexus_common_carto_pb2.pyi
plexus/msgs/plexus_common_entity_pb2.py
plexus/msgs/plexus_common_entity_pb2.pyi
plexus/msgs/plexus_common_geom_pb2.py
plexus/msgs/plexus_common_geom_pb2.pyi
plexus/msgs/plexus_common_message_pb2.py
plexus/msgs/plexus_common_message_pb2.pyi
plexus/msgs/plexus_common_pb2.py
plexus/msgs/plexus_common_pb2.pyi
plexus/msgs/plexus_pb2.py
plexus/msgs/plexus_pb2.pyi
plexus/msgs/utils.py
plexus/msgs/control/__init__.py
plexus/msgs/control/plexus_msgs_control_control_command_pb2.py
plexus/msgs/control/plexus_msgs_control_control_command_pb2.pyi
plexus/msgs/control/plexus_msgs_control_dbw_command_pb2.py
plexus/msgs/control/plexus_msgs_control_dbw_command_pb2.pyi
plexus/msgs/localization/__init__.py
plexus/msgs/localization/plexus_msgs_localization_odometry_pb2.py
plexus/msgs/localization/plexus_msgs_localization_odometry_pb2.pyi
plexus/msgs/localization/plexus_msgs_localization_positioning_pb2.py
plexus/msgs/localization/plexus_msgs_localization_positioning_pb2.pyi
plexus/msgs/mapping/__init__.py
plexus/msgs/mapping/plexus_msgs_mapping_map_region_pb2.py
plexus/msgs/mapping/plexus_msgs_mapping_map_region_pb2.pyi
plexus/msgs/perception/__init__.py
plexus/msgs/perception/plexus_msgs_perception_lane_detection_pb2.py
plexus/msgs/perception/plexus_msgs_perception_lane_detection_pb2.pyi
plexus/msgs/perception/plexus_msgs_perception_obstacle_detection_pb2.py
plexus/msgs/perception/plexus_msgs_perception_obstacle_detection_pb2.pyi
plexus/msgs/planning/__init__.py
plexus/msgs/planning/plexus_msgs_planning_driving_trajectory_pb2.py
plexus/msgs/planning/plexus_msgs_planning_driving_trajectory_pb2.pyi
plexus/msgs/planning/plexus_msgs_planning_obstacle_threat_pb2.py
plexus/msgs/planning/plexus_msgs_planning_obstacle_threat_pb2.pyi
plexus/msgs/routing/__init__.py
plexus/msgs/routing/plexus_msgs_routing_navigation_info_pb2.py
plexus_msgs_python-1.0.12.dist-info/METADATA
plexus_msgs_python-1.0.12.dist-info/WHEEL
plexus_msgs_python-1.0.12.dist-info/entry_points.txt
plexus_msgs_python-1.0.12.dist-info/top_level.txt
plexus_msgs_python-1.0.12.dist-info/RECORD
